QianrushiLinuxZhishiku/README.md
QianrushiLinuxZhishiku/__init__.py
QianrushiLinuxZhishiku/__main__.py
QianrushiLinuxZhishiku/file.epub
QianrushiLinuxZhishiku/index.html
QianrushiLinuxZhishiku/css/__init__.py
QianrushiLinuxZhishiku/css/annotations.css
QianrushiLinuxZhishiku/css/main.css
QianrushiLinuxZhishiku/css/normalize.css
QianrushiLinuxZhishiku/css/popup.css
QianrushiLinuxZhishiku/font/__init__.py
QianrushiLinuxZhishiku/font/fontello.eot
QianrushiLinuxZhishiku/font/fontello.svg
QianrushiLinuxZhishiku/font/fontello.ttf
QianrushiLinuxZhishiku/font/fontello.woff
QianrushiLinuxZhishiku/img/__init__.py
QianrushiLinuxZhishiku/img/annotator-glyph-sprite.png
QianrushiLinuxZhishiku/img/annotator-icon-sprite.png
QianrushiLinuxZhishiku/img/apple-touch-icon.png
QianrushiLinuxZhishiku/img/cancelfullscreen.png
QianrushiLinuxZhishiku/img/close.png
QianrushiLinuxZhishiku/img/fullscreen.png
QianrushiLinuxZhishiku/img/loader.gif
QianrushiLinuxZhishiku/img/menu-icon.png
QianrushiLinuxZhishiku/img/save.png
QianrushiLinuxZhishiku/img/saved.png
QianrushiLinuxZhishiku/img/settings-s.png
QianrushiLinuxZhishiku/img/settings.png
QianrushiLinuxZhishiku/img/star.png
QianrushiLinuxZhishiku/js/__init__.py
QianrushiLinuxZhishiku/js/epub.js
QianrushiLinuxZhishiku/js/epub.min.js
QianrushiLinuxZhishiku/js/epub.min.map
QianrushiLinuxZhishiku/js/hooks.min.js
QianrushiLinuxZhishiku/js/hooks.min.map
QianrushiLinuxZhishiku/js/reader.js
QianrushiLinuxZhishiku/js/reader.js.map
QianrushiLinuxZhishiku/js/reader.min.js
QianrushiLinuxZhishiku/js/reader.min.map
QianrushiLinuxZhishiku/js/hooks/__init__.py
QianrushiLinuxZhishiku/js/hooks/extensions/__init__.py
QianrushiLinuxZhishiku/js/hooks/extensions/highlight.js
QianrushiLinuxZhishiku/js/libs/__init__.py
QianrushiLinuxZhishiku/js/libs/jquery.min.js
QianrushiLinuxZhishiku/js/libs/localforage.min.js
QianrushiLinuxZhishiku/js/libs/screenfull.js
QianrushiLinuxZhishiku/js/libs/screenfull.min.js
QianrushiLinuxZhishiku/js/libs/zip.min.js
qianrushi_linux_zhishiku-2024.3.1.0.dist-info/METADATA
qianrushi_linux_zhishiku-2024.3.1.0.dist-info/WHEEL
qianrushi_linux_zhishiku-2024.3.1.0.dist-info/entry_points.txt
qianrushi_linux_zhishiku-2024.3.1.0.dist-info/top_level.txt
qianrushi_linux_zhishiku-2024.3.1.0.dist-info/RECORD
